Workbook
Name aporte: Planilha1!$D$19
Name patrimonio: Planilha1!$D$22
Name qtd_anos: Planilha1!$D$20
Name rendimento_carteira: Planilha1!$D$14
Name salario: Planilha1!$D$13
Name sugestao_investimento: Planilha1!$D$15
Name taxa_mensal: Planilha1!$D$21

Sheet Planilha1
B12: Configuracoes
B13: Salario | D13: 5000
B14: Rendimento Carteira | D14: 0.006
B15: Sugestao de Investimento (30%) | D15: =salario*30% -> 1500
B18: Investimento Mensal
B19: Ivestimento por mês? | D19: 200
B20: Por quantos anos? | D20: 14
B21: Taxa de Rendimento mensal: | D21: 0.01079
B22: Patrimônio acumulado: | D22: =FV(taxa_mensal,qtd_anos*12,aporte*-1) -> 93936.706
B23: Dividendos mensais: | D23: =patrimonio*rendimento_carteira -> 563.62024
B26: Cenarios | D26: Dividendo
A27: 2 | B27: Investimento em 2 anos: | C27: =FV($D$21,$A27*12,$D$19*-1) -> 5445.5255 | D27: =C27*rendimento_carteira -> 32.673153
A28: 5 | B28: Investimento em 5 anos: | C28: =FV($D$21,$A28*12,$D$19*-1) -> 16755.383 | D28: =C28*rendimento_carteira -> 100.5323
A29: 10 | B29: Investimento em 10 anos: | C29: =FV($D$21,$A29*12,$D$19*-1) -> 48656.843 | D29: =C29*rendimento_carteira -> 291.94106
A30: 20 | B30: Investimento em 20 anos: | C30: =FV($D$21,$A30*12,$D$19*-1) -> 225039.68 | D30: =C30*rendimento_carteira -> 1350.2381
A31: 30 | B31: Investimento em 30 anos: | C31: =FV($D$21,$A31*12,$D$19*-1) -> 864433.93 | D31: =C31*rendimento_carteira -> 5186.6036
B34: PERFIL | C34: Conservador
B35: VALOR A SER INVESTIDO POR MES | C35: =aporte -> 200
B37: TIPO DE FII | C37: Percentual Sugerido | D37: Valores
B38: Papel | C38: =VLOOKUP($C$34&"-"&$B38,Planilha2!$B:$E,4,FALSE) -> 0.3 | D38: =C38*$C$35 -> 60
B39: Tijolo | C39: =VLOOKUP($C$34&"-"&$B39,Planilha2!$B:$E,4,FALSE) -> 0.5 | D39: =C39*$C$35 -> 100
B40: Hibrido | C40: =VLOOKUP($C$34&"-"&$B40,Planilha2!$B:$E,4,FALSE) -> 0.1 | D40: =C40*$C$35 -> 20
B41: FOFs | C41: =VLOOKUP($C$34&"-"&$B41,Planilha2!$B:$E,4,FALSE) -> 0.1 | D41: =C41*$C$35 -> 20
B42: Desenvolvimento | C42: =VLOOKUP($C$34&"-"&$B42,Planilha2!$B:$E,4,FALSE) -> 0 | D42: =C42*$C$35 -> 0
B43: Hotelaria | C43: =VLOOKUP($C$34&"-"&$B43,Planilha2!$B:$E,4,FALSE) -> 0 | D43: =C43*$C$35 -> 0
B44: TOTAL | D44: =SUM(D38:D43) -> 200

Sheet Planilha2
B2: CHAVE | C2: PERFIL | D2: TIPO DE FII | E2: %
B3: Conservador-Papel | C3: Conservador | D3: Papel | E3: 0.3 | I3: EXEMPLO PROCV | J3: %
B4: Conservador-Tijolo | C4: Conservador | D4: Tijolo | E4: 0.5 | I4: Conservador-Tijolo | J4: =VLOOKUP(I4,B:E,4,FALSE) -> 0.5
B5: Conservador-Hibrido | C5: Conservador | D5: Hibrido | E5: 0.1
B6: Conservador-FOFs | C6: Conservador | D6: FOFs | E6: 0.1
B7: Conservador-Desenvolvimento | C7: Conservador | D7: Desenvolvimento | E7: 0
B8: Conservador-Hotelaria | C8: Conservador | D8: Hotelaria | E8: 0
B9: Moderado-Papel | C9: Moderado | D9: Papel | E9: 0.3
B10: Moderado-Tijolo | C10: Moderado | D10: Tijolo | E10: 0.4
B11: Moderado-Hibrido | C11: Moderado | D11: Hibrido | E11: 0.05
B12: Moderado-FOFs | C12: Moderado | D12: FOFs | E12: 0.1
B13: Moderado-Desenvolvimento | C13: Moderado | D13: Desenvolvimento | E13: 0.1
B14: Moderado-Hotelaria | C14: Moderado | D14: Hotelaria | E14: 0.05
B15: Agressivo-Papel | C15: Agressivo | D15: Papel | E15: 0.5
B16: Agressivo-Tijolo | C16: Agressivo | D16: Tijolo | E16: 0.1
... B20: Agressivo-Hotelaria | C20: Agressivo | D20: Hotelaria | E20: 0.1
